meteodbconnector/DBConnector.py
meteodbconnector/__init__.py
MeteoDBconnector-0.1.2.dist-info/METADATA
MeteoDBconnector-0.1.2.dist-info/WHEEL
MeteoDBconnector-0.1.2.dist-info/top_level.txt
MeteoDBconnector-0.1.2.dist-info/RECORD
